__init__.py
avar.py
avar-1.0.4.dist-info/licenses/LICENSE.txt
avar-1.0.4.dist-info/METADATA
avar-1.0.4.dist-info/WHEEL
avar-1.0.4.dist-info/top_level.txt
avar-1.0.4.dist-info/RECORD
