Metadata-Version: 2.4
Name: avar
Version: 1.0.4
Summary: Allan variance tools
Author-email: David Woodburn <david.woodburn@icloud.com>
License: MIT
Project-URL: Homepage, https://gitlab.com/davidwoodburn/avar
Project-URL: Bug Tracker, https://gitlab.com/davidwoodburn/avar/-/issues
Classifier: Programming Language :: Python :: 3
Classifier: License :: OSI Approved :: MIT License
Classifier: Operating System :: OS Independent
Requires-Python: >=3.6
License-File: LICENSE.txt
Requires-Dist: numpy
Requires-Dist: scipy
Requires-Dist: matplotlib
Provides-Extra: test
Requires-Dist: pytest; extra == "test"
Dynamic: license-file
